easyua/Brand.py
easyua/easy_ua.py
easyua-1.0.3.dist-info/METADATA
easyua-1.0.3.dist-info/WHEEL
easyua-1.0.3.dist-info/top_level.txt
easyua-1.0.3.dist-info/RECORD
